any2xl-0.1.dist-info/DESCRIPTION.rst
any2xl-0.1.dist-info/top_level.txt
any2xl-0.1.dist-info/METADATA
any2xl-0.1.dist-info/RECORD
any2xl-0.1.dist-info/WHEEL
any2xl-0.1.dist-info/metadata.json
any2xl-0.1.dist-info/entry_points.txt
any2xl/main.py
any2xl/__init__.py
