Metadata-Version: 2.0
Name: any2xl
Version: 0.1
Summary: A library to generate Excel files from Python iterables
Home-page: https://bitbucket.org/faide/any2xl
Author: Florent Aide
Author-email: florent.aide@gmail.com
License: BSD
Keywords: xls xlsx adapter
Platform: UNKNOWN
Classifier: Development Status :: 3 - Alpha
Classifier: Intended Audience :: Developers
Classifier: License :: OSI Approved :: BSD License
Classifier: Operating System :: OS Independent
Classifier: Programming Language :: Python
Classifier: Topic :: Software Development :: Libraries :: Python Modules
Classifier: Topic :: Office/Business :: Financial :: Spreadsheet
Requires-Dist: six
Requires-Dist: any2 (>=0.3)
Requires-Dist: openpyxl
